giaola_xml_delta-2.0.0.dist-info/DESCRIPTION.rst
giaola_xml_delta-2.0.0.dist-info/METADATA
giaola_xml_delta-2.0.0.dist-info/RECORD
giaola_xml_delta-2.0.0.dist-info/WHEEL
giaola_xml_delta-2.0.0.dist-info/entry_points.txt
giaola_xml_delta-2.0.0.dist-info/metadata.json
giaola_xml_delta-2.0.0.dist-info/top_level.txt
xml_delta/__init__.py
xml_delta/bulk_xml_parser.py
xml_delta/cli.py
xml_delta/core.py
xml_delta/delta.py
xml_delta/delta_task.py
xml_delta/models.py
xml_delta/network_manager.py
xml_delta/settings.py
xml_delta/storage_manager.py
xml_delta/utils.py
