Metadata-Version: 2.0
Name: giaola-xml-delta
Version: 2.0.0
Summary: Package to find differences between big xml files.
Home-page: https://bitbucket.org/giaola/11888_delta
Author: Dimitris Klouvas | Marsel Tzatzo
Author-email: tmarselg@gmail.com
License: UNKNOWN
Keywords: xml
Platform: UNKNOWN
Classifier: Development Status :: 5 - Production/Stable
Classifier: Intended Audience :: Developers
Classifier: Natural Language :: English
Classifier: Programming Language :: Python :: 2
Classifier: Programming Language :: Python :: 2.7
Requires-Dist: SQLAlchemy (==1.1)
Requires-Dist: SQLAlchemy-Paginator (==0.1)
Requires-Dist: alembic (==0.9.6)
Requires-Dist: click (==6.7)
Requires-Dist: giaola-xml-utils (>=0.4.0)
Requires-Dist: psycopg2 (==2.7)
Requires-Dist: requests (==2.18)
Requires-Dist: watchdog (==0.8)
